melina.py
melina-0.1.dist-info/DESCRIPTION.rst
melina-0.1.dist-info/LICENSE.txt
melina-0.1.dist-info/METADATA
melina-0.1.dist-info/RECORD
melina-0.1.dist-info/WHEEL
melina-0.1.dist-info/entry_points.txt
melina-0.1.dist-info/metadata.json
melina-0.1.dist-info/top_level.txt
