Metadata-Version: 2.0
Name: melina
Version: 0.1
Summary: melina: meta/xml converter
Home-page: https://github.com/aurzenligl/melina
Author: Krzysztof Laskowski
Author-email: krzysztof.laskowski@nokia.com
License: MIT license
Keywords: idl compiler
Platform: UNKNOWN
Classifier: Development Status :: 3 - Alpha
Classifier: Intended Audience :: Developers
Classifier: Intended Audience :: Telecommunications Industry
Classifier: Topic :: Scientific/Engineering :: Interface Engine/Protocol Translator
Classifier: Topic :: Software Development :: Code Generators
Classifier: Topic :: Software Development :: Compilers
Classifier: Topic :: Utilities
Classifier: Programming Language :: Python
Classifier: Programming Language :: Python :: 2
Classifier: Programming Language :: Python :: 2.7
Classifier: Operating System :: OS Independent
Classifier: License :: OSI Approved :: MIT License
Requires: lxml
Requires-Dist: lxml
